ezenum/__init__.py
ezenum/_version.py
ezenum/core.py
ezenum-0.0.3.dist-info/LICENSE
ezenum-0.0.3.dist-info/METADATA
ezenum-0.0.3.dist-info/WHEEL
ezenum-0.0.3.dist-info/top_level.txt
ezenum-0.0.3.dist-info/RECORD
